fmo_manual_collector/__init__.py
fmo_manual_collector/util_fmo_manual_collection.py
fmo_manual_collector-0.0.10.dist-info/LICENSE
fmo_manual_collector-0.0.10.dist-info/METADATA
fmo_manual_collector-0.0.10.dist-info/WHEEL
fmo_manual_collector-0.0.10.dist-info/top_level.txt
fmo_manual_collector-0.0.10.dist-info/RECORD
